station/plugin/plugin1/__init__.py
station/plugin/plugin1/constants.py
station/plugin/plugin1/plugin.py
station_plugin1-1.0.1.dist-info/METADATA
station_plugin1-1.0.1.dist-info/WHEEL
station_plugin1-1.0.1.dist-info/top_level.txt
station_plugin1-1.0.1.dist-info/RECORD
