Metadata-Version: 2.1
Name: station-plugin1
Version: 1.0.1
Summary: Station plugin : plugin 1
License: Station Corp Software License Agreement
